<?xml version="1.0" encoding="utf-8"?>
<!--Detailed report on module math-->
<CCCC_Project>
<module_summary>
<lines_of_code value="541" level="1" />
<lines_of_code_per_member_function value="******" level="0" />
<McCabes_cyclomatic_complexity value="89" level="0" />
<McCabes_cyclomatic_complexity_per_member_function value="******" level="2" />
<lines_of_code value="359" level="0" />
<lines_of_code_per_member_function value="********" level="2" />
<lines_of_code_per_line_of_comment value="1.507" level="0" />
<McCabes_cyclomatic_complexity_per_line_of_comment value="0.248" level="0" />
<weighted_methods_per_class_unity value="41" level="0" />
<weighted_methods_per_class_visibility value="0" level="0" />
<depth_of_inheritance_tree value="0" level="0" />
<number_of_children value="0" level="0" />
<coupling_between_objects value="5" level="0" />
<IF4 value="0" level="0" />
<IF4_per_member_function value="********" level="0" />
<IF4_visible value="0" level="0" />
<IF4_visible_per_member_function value="********" level="0" />
<IF4_concrete value="0" level="0" />
<IF4_concrete_per_member_function value="********" level="0" />
</module_summary>
<module_detail>
<description>definition</description>
<source_reference file="../src/mae/fl/math.hpp" line="32" />
<lines_of_code value="4" level="0" />
<McCabes_cyclomatic_complexity value="0" level="0" />
<lines_of_comment value="0" level="0" />
<lines_of_code_per_line_of_comment value="------" level="0" />
<McCabes_cyclomatic_complexity_per_line_of_comment value="------" level="0" />
</module_detail>
<procedural_detail>
<member_function>
<name>are_collinear(Vec3d,Vec3d)</name>
<extent>
<description>declaration</description>
<source_reference file="../src/mae/fl/math.hpp" line="319" />
</extent>
<extent>
<description>definition</description>
<source_reference file="../src/mae/fl/math.cpp" line="600" />
</extent>
<lines_of_code value="7" level="0" />
<McCabes_cyclomatic_complexity value="6" level="0" />
<lines_of_comment value="9" level="0" />
<lines_of_code_per_line_of_comment value="------" level="0" />
<McCabes_cyclomatic_complexity_per_line_of_comment value="0.667" level="0" />
</member_function>
<member_function>
<name>calc_angle_half(Vec3d,Vec3d)</name>
<extent>
<description>declaration</description>
<source_reference file="../src/mae/fl/math.hpp" line="366" />
</extent>
<extent>
<description>definition</description>
<source_reference file="../src/mae/fl/math.cpp" line="670" />
</extent>
<lines_of_code value="12" level="0" />
<McCabes_cyclomatic_complexity value="5" level="0" />
<lines_of_comment value="8" level="0" />
<lines_of_code_per_line_of_comment value="------" level="0" />
<McCabes_cyclomatic_complexity_per_line_of_comment value="0.625" level="0" />
</member_function>
<member_function>
<name>calc_angle_half_deg(Vec3d,Vec3d)</name>
<extent>
<description>declaration</description>
<source_reference file="../src/mae/fl/math.hpp" line="375" />
</extent>
<extent>
<description>definition</description>
<source_reference file="../src/mae/fl/math.cpp" line="686" />
</extent>
<lines_of_code value="5" level="0" />
<McCabes_cyclomatic_complexity value="1" level="0" />
<lines_of_comment value="7" level="0" />
<lines_of_code_per_line_of_comment value="------" level="0" />
<McCabes_cyclomatic_complexity_per_line_of_comment value="------" level="0" />
</member_function>
<member_function>
<name>calc_angle_plane(Vec3d,Vec3d,Vec3d)</name>
<extent>
<description>declaration</description>
<source_reference file="../src/mae/fl/math.hpp" line="347" />
</extent>
<extent>
<description>definition</description>
<source_reference file="../src/mae/fl/math.cpp" line="652" />
</extent>
<lines_of_code value="11" level="0" />
<McCabes_cyclomatic_complexity value="1" level="0" />
<lines_of_comment value="66" level="0" />
<lines_of_code_per_line_of_comment value="------" level="0" />
<McCabes_cyclomatic_complexity_per_line_of_comment value="------" level="0" />
</member_function>
<member_function>
<name>calc_angle_plane_deg(Vec3d,Vec3d,Vec3d)</name>
<extent>
<description>declaration</description>
<source_reference file="../src/mae/fl/math.hpp" line="357" />
</extent>
<extent>
<description>definition</description>
<source_reference file="../src/mae/fl/math.cpp" line="665" />
</extent>
<lines_of_code value="5" level="0" />
<McCabes_cyclomatic_complexity value="1" level="0" />
<lines_of_comment value="8" level="0" />
<lines_of_code_per_line_of_comment value="------" level="0" />
<McCabes_cyclomatic_complexity_per_line_of_comment value="------" level="0" />
</member_function>
<member_function>
<name>deg_to_rad(double)</name>
<extent>
<description>declaration</description>
<source_reference file="../src/mae/fl/math.hpp" line="310" />
</extent>
<extent>
<description>definition</description>
<source_reference file="../src/mae/fl/math.cpp" line="696" />
</extent>
<lines_of_code value="5" level="0" />
<McCabes_cyclomatic_complexity value="1" level="0" />
<lines_of_comment value="6" level="0" />
<lines_of_code_per_line_of_comment value="------" level="0" />
<McCabes_cyclomatic_complexity_per_line_of_comment value="------" level="0" />
</member_function>
<member_function>
<name>fmod_pos(double,double)</name>
<extent>
<description>declaration</description>
<source_reference file="../src/mae/fl/math.hpp" line="384" />
</extent>
<extent>
<description>definition</description>
<source_reference file="../src/mae/fl/math.cpp" line="701" />
</extent>
<lines_of_code value="10" level="0" />
<McCabes_cyclomatic_complexity value="2" level="0" />
<lines_of_comment value="7" level="0" />
<lines_of_code_per_line_of_comment value="------" level="0" />
<McCabes_cyclomatic_complexity_per_line_of_comment value="------" level="0" />
</member_function>
<member_function>
<name>joint_to_vec(shared_ptr)</name>
<extent>
<description>declaration</description>
<source_reference file="../src/mae/fl/math.hpp" line="42" />
</extent>
<extent>
<description>definition</description>
<source_reference file="../src/mae/fl/math.cpp" line="15" />
</extent>
<lines_of_code value="9" level="0" />
<McCabes_cyclomatic_complexity value="1" level="0" />
<lines_of_comment value="6" level="0" />
<lines_of_code_per_line_of_comment value="------" level="0" />
<McCabes_cyclomatic_complexity_per_line_of_comment value="------" level="0" />
</member_function>
<member_function>
<name>joint_to_vec_fl(shared_ptr)</name>
<extent>
<description>declaration</description>
<source_reference file="../src/mae/fl/math.hpp" line="58" />
</extent>
<extent>
<description>definition</description>
<source_reference file="../src/mae/fl/math.cpp" line="30" />
</extent>
<lines_of_code value="8" level="0" />
<McCabes_cyclomatic_complexity value="1" level="0" />
<lines_of_comment value="6" level="0" />
<lines_of_code_per_line_of_comment value="------" level="0" />
<McCabes_cyclomatic_complexity_per_line_of_comment value="------" level="0" />
</member_function>
<member_function>
<name>maevec_to_vec3d(shared_ptr)</name>
<extent>
<description>declaration</description>
<source_reference file="../src/mae/fl/math.hpp" line="105" />
</extent>
<extent>
<description>definition</description>
<source_reference file="../src/mae/fl/math.cpp" line="108" />
</extent>
<lines_of_code value="9" level="0" />
<McCabes_cyclomatic_complexity value="1" level="0" />
<lines_of_comment value="6" level="0" />
<lines_of_code_per_line_of_comment value="------" level="0" />
<McCabes_cyclomatic_complexity_per_line_of_comment value="------" level="0" />
</member_function>
<member_function>
<name>matrix_mul(Mat,Vec3d)</name>
<extent>
<description>declaration</description>
<source_reference file="../src/mae/fl/math.hpp" line="122" />
</extent>
<extent>
<description>definition</description>
<source_reference file="../src/mae/fl/math.cpp" line="124" />
</extent>
<lines_of_code value="10" level="0" />
<McCabes_cyclomatic_complexity value="1" level="0" />
<lines_of_comment value="8" level="0" />
<lines_of_code_per_line_of_comment value="------" level="0" />
<McCabes_cyclomatic_complexity_per_line_of_comment value="------" level="0" />
</member_function>
<member_function>
<name>matrix_rot_x(double)</name>
<extent>
<description>declaration</description>
<source_reference file="../src/mae/fl/math.hpp" line="259" />
</extent>
<extent>
<description>definition</description>
<source_reference file="../src/mae/fl/math.cpp" line="506" />
</extent>
<lines_of_code value="13" level="0" />
<McCabes_cyclomatic_complexity value="1" level="0" />
<lines_of_comment value="7" level="0" />
<lines_of_code_per_line_of_comment value="------" level="0" />
<McCabes_cyclomatic_complexity_per_line_of_comment value="------" level="0" />
</member_function>
<member_function>
<name>matrix_rot_y(double)</name>
<extent>
<description>declaration</description>
<source_reference file="../src/mae/fl/math.hpp" line="267" />
</extent>
<extent>
<description>definition</description>
<source_reference file="../src/mae/fl/math.cpp" line="522" />
</extent>
<lines_of_code value="13" level="0" />
<McCabes_cyclomatic_complexity value="1" level="0" />
<lines_of_comment value="7" level="0" />
<lines_of_code_per_line_of_comment value="------" level="0" />
<McCabes_cyclomatic_complexity_per_line_of_comment value="------" level="0" />
</member_function>
<member_function>
<name>matrix_rot_z(double)</name>
<extent>
<description>declaration</description>
<source_reference file="../src/mae/fl/math.hpp" line="275" />
</extent>
<extent>
<description>definition</description>
<source_reference file="../src/mae/fl/math.cpp" line="538" />
</extent>
<lines_of_code value="13" level="0" />
<McCabes_cyclomatic_complexity value="1" level="0" />
<lines_of_comment value="7" level="0" />
<lines_of_code_per_line_of_comment value="------" level="0" />
<McCabes_cyclomatic_complexity_per_line_of_comment value="------" level="0" />
</member_function>
<member_function>
<name>matrix_rot_zxy(double,double,double)</name>
<extent>
<description>declaration</description>
<source_reference file="../src/mae/fl/math.hpp" line="285" />
</extent>
<extent>
<description>definition</description>
<source_reference file="../src/mae/fl/math.cpp" line="554" />
</extent>
<lines_of_code value="5" level="0" />
<McCabes_cyclomatic_complexity value="1" level="0" />
<lines_of_comment value="9" level="0" />
<lines_of_code_per_line_of_comment value="------" level="0" />
<McCabes_cyclomatic_complexity_per_line_of_comment value="------" level="0" />
</member_function>
<member_function>
<name>project_back_to_default(...)</name>
<extent>
<description>declaration</description>
<source_reference file="../src/mae/fl/math.hpp" line="178" />
</extent>
<lines_of_code value="1" level="0" />
<McCabes_cyclomatic_complexity value="0" level="0" />
<lines_of_comment value="8" level="0" />
<lines_of_code_per_line_of_comment value="------" level="0" />
<McCabes_cyclomatic_complexity_per_line_of_comment value="------" level="0" />
</member_function>
<member_function>
<name>project_back_to_default(Vec3d,Vec3d,Vec3d,Vec3d,Vec3d)</name>
<extent>
<description>declaration</description>
<source_reference file="../src/mae/fl/math.hpp" line="167" />
</extent>
<extent>
<description>definition</description>
<source_reference file="../src/mae/fl/math.cpp" line="193" />
</extent>
<lines_of_code value="34" level="1" />
<McCabes_cyclomatic_complexity value="5" level="0" />
<lines_of_comment value="13" level="0" />
<lines_of_code_per_line_of_comment value="2.615" level="0" />
<McCabes_cyclomatic_complexity_per_line_of_comment value="0.385" level="0" />
</member_function>
<member_function>
<name>project_back_to_default(shared_ptr,shared_ptr,shared_ptr)</name>
<extent>
<description>definition</description>
<source_reference file="../src/mae/fl/math.cpp" line="235" />
</extent>
<lines_of_code value="8" level="0" />
<McCabes_cyclomatic_complexity value="2" level="0" />
<lines_of_comment value="0" level="0" />
<lines_of_code_per_line_of_comment value="------" level="0" />
<McCabes_cyclomatic_complexity_per_line_of_comment value="------" level="0" />
</member_function>
<member_function>
<name>project_back_to_default_maevec(...)</name>
<extent>
<description>declaration</description>
<source_reference file="../src/mae/fl/math.hpp" line="188" />
</extent>
<lines_of_code value="1" level="0" />
<McCabes_cyclomatic_complexity value="0" level="0" />
<lines_of_comment value="8" level="0" />
<lines_of_code_per_line_of_comment value="------" level="0" />
<McCabes_cyclomatic_complexity_per_line_of_comment value="------" level="0" />
</member_function>
<member_function>
<name>project_back_to_default_maevec(shared_ptr,shared_ptr,shared_ptr)</name>
<extent>
<description>definition</description>
<source_reference file="../src/mae/fl/math.cpp" line="245" />
</extent>
<lines_of_code value="4" level="0" />
<McCabes_cyclomatic_complexity value="1" level="0" />
<lines_of_comment value="0" level="0" />
<lines_of_code_per_line_of_comment value="------" level="0" />
<McCabes_cyclomatic_complexity_per_line_of_comment value="------" level="0" />
</member_function>
<member_function>
<name>project_orthogonal(Vec3d,Vec3d,Vec3d,Vec3d)</name>
<extent>
<description>declaration</description>
<source_reference file="../src/mae/fl/math.hpp" line="200" />
</extent>
<extent>
<description>definition</description>
<source_reference file="../src/mae/fl/math.cpp" line="251" />
</extent>
<lines_of_code value="39" level="1" />
<McCabes_cyclomatic_complexity value="5" level="0" />
<lines_of_comment value="15" level="0" />
<lines_of_code_per_line_of_comment value="2.600" level="0" />
<McCabes_cyclomatic_complexity_per_line_of_comment value="0.333" level="0" />
</member_function>
<member_function>
<name>project_to_basis(...)</name>
<extent>
<description>declaration</description>
<source_reference file="../src/mae/fl/math.hpp" line="144" />
</extent>
<lines_of_code value="1" level="0" />
<McCabes_cyclomatic_complexity value="0" level="0" />
<lines_of_comment value="8" level="0" />
<lines_of_code_per_line_of_comment value="------" level="0" />
<McCabes_cyclomatic_complexity_per_line_of_comment value="------" level="0" />
</member_function>
<member_function>
<name>project_to_basis(Vec3d,Vec3d,Vec3d,Vec3d,Vec3d)</name>
<extent>
<description>declaration</description>
<source_reference file="../src/mae/fl/math.hpp" line="133" />
</extent>
<extent>
<description>definition</description>
<source_reference file="../src/mae/fl/math.cpp" line="136" />
</extent>
<lines_of_code value="34" level="1" />
<McCabes_cyclomatic_complexity value="5" level="0" />
<lines_of_comment value="12" level="0" />
<lines_of_code_per_line_of_comment value="2.833" level="0" />
<McCabes_cyclomatic_complexity_per_line_of_comment value="0.417" level="0" />
</member_function>
<member_function>
<name>project_to_basis(shared_ptr,shared_ptr,shared_ptr)</name>
<extent>
<description>definition</description>
<source_reference file="../src/mae/fl/math.cpp" line="178" />
</extent>
<lines_of_code value="8" level="0" />
<McCabes_cyclomatic_complexity value="2" level="0" />
<lines_of_comment value="0" level="0" />
<lines_of_code_per_line_of_comment value="------" level="0" />
<McCabes_cyclomatic_complexity_per_line_of_comment value="------" level="0" />
</member_function>
<member_function>
<name>project_to_basis_maevec(...)</name>
<extent>
<description>declaration</description>
<source_reference file="../src/mae/fl/math.hpp" line="155" />
</extent>
<lines_of_code value="1" level="0" />
<McCabes_cyclomatic_complexity value="0" level="0" />
<lines_of_comment value="8" level="0" />
<lines_of_code_per_line_of_comment value="------" level="0" />
<McCabes_cyclomatic_complexity_per_line_of_comment value="------" level="0" />
</member_function>
<member_function>
<name>project_to_basis_maevec(shared_ptr,shared_ptr,shared_ptr)</name>
<extent>
<description>definition</description>
<source_reference file="../src/mae/fl/math.cpp" line="188" />
</extent>
<lines_of_code value="4" level="0" />
<McCabes_cyclomatic_complexity value="1" level="0" />
<lines_of_comment value="0" level="0" />
<lines_of_code_per_line_of_comment value="------" level="0" />
<McCabes_cyclomatic_complexity_per_line_of_comment value="------" level="0" />
</member_function>
<member_function>
<name>quaternion(Vec3d,Vec3d)</name>
<extent>
<description>declaration</description>
<source_reference file="../src/mae/fl/math.hpp" line="294" />
</extent>
<extent>
<description>definition</description>
<source_reference file="../src/mae/fl/math.cpp" line="561" />
</extent>
<lines_of_code value="34" level="1" />
<McCabes_cyclomatic_complexity value="4" level="0" />
<lines_of_comment value="8" level="0" />
<lines_of_code_per_line_of_comment value="4.250" level="0" />
<McCabes_cyclomatic_complexity_per_line_of_comment value="------" level="0" />
</member_function>
<member_function>
<name>rad_to_deg(double)</name>
<extent>
<description>declaration</description>
<source_reference file="../src/mae/fl/math.hpp" line="302" />
</extent>
<extent>
<description>definition</description>
<source_reference file="../src/mae/fl/math.cpp" line="691" />
</extent>
<lines_of_code value="5" level="0" />
<McCabes_cyclomatic_complexity value="1" level="0" />
<lines_of_comment value="6" level="0" />
<lines_of_code_per_line_of_comment value="------" level="0" />
<McCabes_cyclomatic_complexity_per_line_of_comment value="------" level="0" />
</member_function>
<member_function>
<name>rotate_around_axis(Vec3d,Vec3d,double)</name>
<extent>
<description>declaration</description>
<source_reference file="../src/mae/fl/math.hpp" line="211" />
</extent>
<extent>
<description>definition</description>
<source_reference file="../src/mae/fl/math.cpp" line="304" />
</extent>
<lines_of_code value="47" level="1" />
<McCabes_cyclomatic_complexity value="7" level="0" />
<lines_of_comment value="12" level="0" />
<lines_of_code_per_line_of_comment value="3.917" level="0" />
<McCabes_cyclomatic_complexity_per_line_of_comment value="0.583" level="0" />
</member_function>
<member_function>
<name>rotate_yzx(Vec3d,double,double,double)</name>
<extent>
<description>declaration</description>
<source_reference file="../src/mae/fl/math.hpp" line="251" />
</extent>
<extent>
<description>definition</description>
<source_reference file="../src/mae/fl/math.cpp" line="493" />
</extent>
<lines_of_code value="11" level="0" />
<McCabes_cyclomatic_complexity value="1" level="0" />
<lines_of_comment value="10" level="0" />
<lines_of_code_per_line_of_comment value="------" level="0" />
<McCabes_cyclomatic_complexity_per_line_of_comment value="------" level="0" />
</member_function>
<member_function>
<name>rotate_zxy(Vec3d,double,double,double)</name>
<extent>
<description>declaration</description>
<source_reference file="../src/mae/fl/math.hpp" line="240" />
</extent>
<extent>
<description>definition</description>
<source_reference file="../src/mae/fl/math.cpp" line="480" />
</extent>
<lines_of_code value="11" level="0" />
<McCabes_cyclomatic_complexity value="1" level="0" />
<lines_of_comment value="10" level="0" />
<lines_of_code_per_line_of_comment value="------" level="0" />
<McCabes_cyclomatic_complexity_per_line_of_comment value="------" level="0" />
</member_function>
<member_function>
<name>rotation_angles_yzx(Vec3d,Vec3d)</name>
<extent>
<description>declaration</description>
<source_reference file="../src/mae/fl/math.hpp" line="229" />
</extent>
<extent>
<description>definition</description>
<source_reference file="../src/mae/fl/math.cpp" line="401" />
</extent>
<lines_of_code value="62" level="1" />
<McCabes_cyclomatic_complexity value="11" level="1" />
<lines_of_comment value="15" level="0" />
<lines_of_code_per_line_of_comment value="4.133" level="0" />
<McCabes_cyclomatic_complexity_per_line_of_comment value="0.733" level="0" />
</member_function>
<member_function>
<name>rotation_angles_zxy(Vec3d,Vec3d)</name>
<extent>
<description>declaration</description>
<source_reference file="../src/mae/fl/math.hpp" line="220" />
</extent>
<extent>
<description>definition</description>
<source_reference file="../src/mae/fl/math.cpp" line="366" />
</extent>
<lines_of_code value="23" level="0" />
<McCabes_cyclomatic_complexity value="4" level="0" />
<lines_of_comment value="12" level="0" />
<lines_of_code_per_line_of_comment value="1.917" level="0" />
<McCabes_cyclomatic_complexity_per_line_of_comment value="------" level="0" />
</member_function>
<member_function>
<name>sign(double)</name>
<extent>
<description>declaration</description>
<source_reference file="../src/mae/fl/math.hpp" line="392" />
</extent>
<extent>
<description>definition</description>
<source_reference file="../src/mae/fl/math.cpp" line="713" />
</extent>
<lines_of_code value="5" level="0" />
<McCabes_cyclomatic_complexity value="1" level="0" />
<lines_of_comment value="6" level="0" />
<lines_of_code_per_line_of_comment value="------" level="0" />
<McCabes_cyclomatic_complexity_per_line_of_comment value="------" level="0" />
</member_function>
<member_function>
<name>stdvec_to_vec2d(vector)</name>
<extent>
<description>declaration</description>
<source_reference file="../src/mae/fl/math.hpp" line="97" />
</extent>
<extent>
<description>definition</description>
<source_reference file="../src/mae/fl/math.cpp" line="88" />
</extent>
<lines_of_code value="17" level="0" />
<McCabes_cyclomatic_complexity value="3" level="0" />
<lines_of_comment value="6" level="0" />
<lines_of_code_per_line_of_comment value="------" level="0" />
<McCabes_cyclomatic_complexity_per_line_of_comment value="------" level="0" />
</member_function>
<member_function>
<name>stdvec_to_vec3d(vector)</name>
<extent>
<description>declaration</description>
<source_reference file="../src/mae/fl/math.hpp" line="89" />
</extent>
<extent>
<description>definition</description>
<source_reference file="../src/mae/fl/math.cpp" line="68" />
</extent>
<lines_of_code value="17" level="0" />
<McCabes_cyclomatic_complexity value="3" level="0" />
<lines_of_comment value="6" level="0" />
<lines_of_code_per_line_of_comment value="------" level="0" />
<McCabes_cyclomatic_complexity_per_line_of_comment value="------" level="0" />
</member_function>
<member_function>
<name>vec3d_to_maevec(Vec3d)</name>
<extent>
<description>declaration</description>
<source_reference file="../src/mae/fl/math.hpp" line="113" />
</extent>
<extent>
<description>definition</description>
<source_reference file="../src/mae/fl/math.cpp" line="119" />
</extent>
<lines_of_code value="5" level="0" />
<McCabes_cyclomatic_complexity value="1" level="0" />
<lines_of_comment value="6" level="0" />
<lines_of_code_per_line_of_comment value="------" level="0" />
<McCabes_cyclomatic_complexity_per_line_of_comment value="------" level="0" />
</member_function>
<member_function>
<name>vec_to_joint(Vec3d)</name>
<extent>
<description>declaration</description>
<source_reference file="../src/mae/fl/math.hpp" line="50" />
</extent>
<extent>
<description>definition</description>
<source_reference file="../src/mae/fl/math.cpp" line="25" />
</extent>
<lines_of_code value="5" level="0" />
<McCabes_cyclomatic_complexity value="1" level="0" />
<lines_of_comment value="6" level="0" />
<lines_of_code_per_line_of_comment value="------" level="0" />
<McCabes_cyclomatic_complexity_per_line_of_comment value="------" level="0" />
</member_function>
<member_function>
<name>vec_to_joint_fl(Vec2d)</name>
<extent>
<description>declaration</description>
<source_reference file="../src/mae/fl/math.hpp" line="66" />
</extent>
<extent>
<description>definition</description>
<source_reference file="../src/mae/fl/math.cpp" line="39" />
</extent>
<lines_of_code value="5" level="0" />
<McCabes_cyclomatic_complexity value="1" level="0" />
<lines_of_comment value="6" level="0" />
<lines_of_code_per_line_of_comment value="------" level="0" />
<McCabes_cyclomatic_complexity_per_line_of_comment value="------" level="0" />
</member_function>
<member_function>
<name>vec_to_stdvec(Vec2d)</name>
<extent>
<description>declaration</description>
<source_reference file="../src/mae/fl/math.hpp" line="81" />
</extent>
<extent>
<description>definition</description>
<source_reference file="../src/mae/fl/math.cpp" line="56" />
</extent>
<lines_of_code value="10" level="0" />
<McCabes_cyclomatic_complexity value="2" level="0" />
<lines_of_comment value="6" level="0" />
<lines_of_code_per_line_of_comment value="------" level="0" />
<McCabes_cyclomatic_complexity_per_line_of_comment value="------" level="0" />
</member_function>
<member_function>
<name>vec_to_stdvec(Vec3d)</name>
<extent>
<description>declaration</description>
<source_reference file="../src/mae/fl/math.hpp" line="73" />
</extent>
<extent>
<description>definition</description>
<source_reference file="../src/mae/fl/math.cpp" line="44" />
</extent>
<lines_of_code value="10" level="0" />
<McCabes_cyclomatic_complexity value="2" level="0" />
<lines_of_comment value="5" level="0" />
<lines_of_code_per_line_of_comment value="------" level="0" />
<McCabes_cyclomatic_complexity_per_line_of_comment value="------" level="0" />
</member_function>
</procedural_detail>
<structural_detail>
<module>
<name>math</name>
<client_module>
</client_module>
<supplier_module>
<name>Mat</name>
<visible>true</visible>
<concrete>true</concrete>
<extent>
<description>pass by value</description>
<source_reference file="../src/mae/fl/math.hpp" line="122" />
</extent>
<extent>
<description>pass by value</description>
<source_reference file="../src/mae/fl/math.cpp" line="124" />
</extent>
<name>Vec2d</name>
<visible>true</visible>
<concrete>true</concrete>
<extent>
<description>pass by value</description>
<source_reference file="../src/mae/fl/math.hpp" line="66" />
</extent>
<extent>
<description>pass by value</description>
<source_reference file="../src/mae/fl/math.hpp" line="81" />
</extent>
<extent>
<description>pass by value</description>
<source_reference file="../src/mae/fl/math.cpp" line="39" />
</extent>
<extent>
<description>pass by value</description>
<source_reference file="../src/mae/fl/math.cpp" line="56" />
</extent>
<name>Vec3d</name>
<visible>true</visible>
<concrete>true</concrete>
<extent>
<description>pass by value</description>
<source_reference file="../src/mae/fl/math.hpp" line="50" />
</extent>
<extent>
<description>pass by value</description>
<source_reference file="../src/mae/fl/math.hpp" line="73" />
</extent>
<extent>
<description>pass by value</description>
<source_reference file="../src/mae/fl/math.hpp" line="113" />
</extent>
<extent>
<description>pass by value</description>
<source_reference file="../src/mae/fl/math.hpp" line="122" />
</extent>
<extent>
<description>pass by value</description>
<source_reference file="../src/mae/fl/math.hpp" line="133" />
</extent>
<extent>
<description>pass by value</description>
<source_reference file="../src/mae/fl/math.hpp" line="133" />
</extent>
<extent>
<description>pass by value</description>
<source_reference file="../src/mae/fl/math.hpp" line="133" />
</extent>
<extent>
<description>pass by value</description>
<source_reference file="../src/mae/fl/math.hpp" line="133" />
</extent>
<extent>
<description>pass by value</description>
<source_reference file="../src/mae/fl/math.hpp" line="134" />
</extent>
<extent>
<description>pass by value</description>
<source_reference file="../src/mae/fl/math.hpp" line="167" />
</extent>
<extent>
<description>pass by value</description>
<source_reference file="../src/mae/fl/math.hpp" line="167" />
</extent>
<extent>
<description>pass by value</description>
<source_reference file="../src/mae/fl/math.hpp" line="167" />
</extent>
<extent>
<description>pass by value</description>
<source_reference file="../src/mae/fl/math.hpp" line="167" />
</extent>
<extent>
<description>pass by value</description>
<source_reference file="../src/mae/fl/math.hpp" line="168" />
</extent>
<extent>
<description>pass by value</description>
<source_reference file="../src/mae/fl/math.hpp" line="200" />
</extent>
<extent>
<description>pass by value</description>
<source_reference file="../src/mae/fl/math.hpp" line="200" />
</extent>
<extent>
<description>pass by value</description>
<source_reference file="../src/mae/fl/math.hpp" line="200" />
</extent>
<extent>
<description>pass by value</description>
<source_reference file="../src/mae/fl/math.hpp" line="201" />
</extent>
<extent>
<description>pass by value</description>
<source_reference file="../src/mae/fl/math.hpp" line="211" />
</extent>
<extent>
<description>pass by value</description>
<source_reference file="../src/mae/fl/math.hpp" line="211" />
</extent>
<extent>
<description>pass by value</description>
<source_reference file="../src/mae/fl/math.hpp" line="220" />
</extent>
<extent>
<description>pass by value</description>
<source_reference file="../src/mae/fl/math.hpp" line="220" />
</extent>
<extent>
<description>pass by value</description>
<source_reference file="../src/mae/fl/math.hpp" line="229" />
</extent>
<extent>
<description>pass by value</description>
<source_reference file="../src/mae/fl/math.hpp" line="229" />
</extent>
<extent>
<description>pass by value</description>
<source_reference file="../src/mae/fl/math.hpp" line="240" />
</extent>
<extent>
<description>pass by value</description>
<source_reference file="../src/mae/fl/math.hpp" line="251" />
</extent>
<extent>
<description>pass by value</description>
<source_reference file="../src/mae/fl/math.hpp" line="294" />
</extent>
<extent>
<description>pass by value</description>
<source_reference file="../src/mae/fl/math.hpp" line="294" />
</extent>
<extent>
<description>pass by value</description>
<source_reference file="../src/mae/fl/math.hpp" line="319" />
</extent>
<extent>
<description>pass by value</description>
<source_reference file="../src/mae/fl/math.hpp" line="319" />
</extent>
<extent>
<description>pass by value</description>
<source_reference file="../src/mae/fl/math.hpp" line="347" />
</extent>
<extent>
<description>pass by value</description>
<source_reference file="../src/mae/fl/math.hpp" line="347" />
</extent>
<extent>
<description>pass by value</description>
<source_reference file="../src/mae/fl/math.hpp" line="347" />
</extent>
<extent>
<description>pass by value</description>
<source_reference file="../src/mae/fl/math.hpp" line="357" />
</extent>
<extent>
<description>pass by value</description>
<source_reference file="../src/mae/fl/math.hpp" line="357" />
</extent>
<extent>
<description>pass by value</description>
<source_reference file="../src/mae/fl/math.hpp" line="357" />
</extent>
<extent>
<description>pass by value</description>
<source_reference file="../src/mae/fl/math.hpp" line="366" />
</extent>
<extent>
<description>pass by value</description>
<source_reference file="../src/mae/fl/math.hpp" line="366" />
</extent>
<extent>
<description>pass by value</description>
<source_reference file="../src/mae/fl/math.hpp" line="375" />
</extent>
<extent>
<description>pass by value</description>
<source_reference file="../src/mae/fl/math.hpp" line="375" />
</extent>
<extent>
<description>pass by value</description>
<source_reference file="../src/mae/fl/math.cpp" line="25" />
</extent>
<extent>
<description>pass by value</description>
<source_reference file="../src/mae/fl/math.cpp" line="44" />
</extent>
<extent>
<description>pass by value</description>
<source_reference file="../src/mae/fl/math.cpp" line="119" />
</extent>
<extent>
<description>pass by value</description>
<source_reference file="../src/mae/fl/math.cpp" line="124" />
</extent>
<extent>
<description>pass by value</description>
<source_reference file="../src/mae/fl/math.cpp" line="136" />
</extent>
<extent>
<description>pass by value</description>
<source_reference file="../src/mae/fl/math.cpp" line="136" />
</extent>
<extent>
<description>pass by value</description>
<source_reference file="../src/mae/fl/math.cpp" line="136" />
</extent>
<extent>
<description>pass by value</description>
<source_reference file="../src/mae/fl/math.cpp" line="136" />
</extent>
<extent>
<description>pass by value</description>
<source_reference file="../src/mae/fl/math.cpp" line="137" />
</extent>
<extent>
<description>pass by value</description>
<source_reference file="../src/mae/fl/math.cpp" line="193" />
</extent>
<extent>
<description>pass by value</description>
<source_reference file="../src/mae/fl/math.cpp" line="193" />
</extent>
<extent>
<description>pass by value</description>
<source_reference file="../src/mae/fl/math.cpp" line="193" />
</extent>
<extent>
<description>pass by value</description>
<source_reference file="../src/mae/fl/math.cpp" line="193" />
</extent>
<extent>
<description>pass by value</description>
<source_reference file="../src/mae/fl/math.cpp" line="194" />
</extent>
<extent>
<description>pass by value</description>
<source_reference file="../src/mae/fl/math.cpp" line="251" />
</extent>
<extent>
<description>pass by value</description>
<source_reference file="../src/mae/fl/math.cpp" line="251" />
</extent>
<extent>
<description>pass by value</description>
<source_reference file="../src/mae/fl/math.cpp" line="251" />
</extent>
<extent>
<description>pass by value</description>
<source_reference file="../src/mae/fl/math.cpp" line="252" />
</extent>
<extent>
<description>pass by value</description>
<source_reference file="../src/mae/fl/math.cpp" line="304" />
</extent>
<extent>
<description>pass by value</description>
<source_reference file="../src/mae/fl/math.cpp" line="304" />
</extent>
<extent>
<description>pass by value</description>
<source_reference file="../src/mae/fl/math.cpp" line="366" />
</extent>
<extent>
<description>pass by value</description>
<source_reference file="../src/mae/fl/math.cpp" line="366" />
</extent>
<extent>
<description>pass by value</description>
<source_reference file="../src/mae/fl/math.cpp" line="401" />
</extent>
<extent>
<description>pass by value</description>
<source_reference file="../src/mae/fl/math.cpp" line="401" />
</extent>
<extent>
<description>pass by value</description>
<source_reference file="../src/mae/fl/math.cpp" line="480" />
</extent>
<extent>
<description>pass by value</description>
<source_reference file="../src/mae/fl/math.cpp" line="493" />
</extent>
<extent>
<description>pass by value</description>
<source_reference file="../src/mae/fl/math.cpp" line="561" />
</extent>
<extent>
<description>pass by value</description>
<source_reference file="../src/mae/fl/math.cpp" line="561" />
</extent>
<extent>
<description>pass by value</description>
<source_reference file="../src/mae/fl/math.cpp" line="600" />
</extent>
<extent>
<description>pass by value</description>
<source_reference file="../src/mae/fl/math.cpp" line="600" />
</extent>
<extent>
<description>pass by value</description>
<source_reference file="../src/mae/fl/math.cpp" line="652" />
</extent>
<extent>
<description>pass by value</description>
<source_reference file="../src/mae/fl/math.cpp" line="652" />
</extent>
<extent>
<description>pass by value</description>
<source_reference file="../src/mae/fl/math.cpp" line="652" />
</extent>
<extent>
<description>pass by value</description>
<source_reference file="../src/mae/fl/math.cpp" line="665" />
</extent>
<extent>
<description>pass by value</description>
<source_reference file="../src/mae/fl/math.cpp" line="665" />
</extent>
<extent>
<description>pass by value</description>
<source_reference file="../src/mae/fl/math.cpp" line="665" />
</extent>
<extent>
<description>pass by value</description>
<source_reference file="../src/mae/fl/math.cpp" line="670" />
</extent>
<extent>
<description>pass by value</description>
<source_reference file="../src/mae/fl/math.cpp" line="670" />
</extent>
<extent>
<description>pass by value</description>
<source_reference file="../src/mae/fl/math.cpp" line="686" />
</extent>
<extent>
<description>pass by value</description>
<source_reference file="../src/mae/fl/math.cpp" line="686" />
</extent>
<name>shared_ptr</name>
<visible>true</visible>
<concrete>true</concrete>
<extent>
<description>pass by value</description>
<source_reference file="../src/mae/fl/math.hpp" line="42" />
</extent>
<extent>
<description>pass by value</description>
<source_reference file="../src/mae/fl/math.hpp" line="58" />
</extent>
<extent>
<description>pass by value</description>
<source_reference file="../src/mae/fl/math.hpp" line="105" />
</extent>
<extent>
<description>pass by value</description>
<source_reference file="../src/mae/fl/math.cpp" line="15" />
</extent>
<extent>
<description>pass by value</description>
<source_reference file="../src/mae/fl/math.cpp" line="30" />
</extent>
<extent>
<description>pass by value</description>
<source_reference file="../src/mae/fl/math.cpp" line="108" />
</extent>
<extent>
<description>pass by value</description>
<source_reference file="../src/mae/fl/math.cpp" line="178" />
</extent>
<extent>
<description>pass by value</description>
<source_reference file="../src/mae/fl/math.cpp" line="178" />
</extent>
<extent>
<description>pass by value</description>
<source_reference file="../src/mae/fl/math.cpp" line="178" />
</extent>
<extent>
<description>pass by value</description>
<source_reference file="../src/mae/fl/math.cpp" line="188" />
</extent>
<extent>
<description>pass by value</description>
<source_reference file="../src/mae/fl/math.cpp" line="188" />
</extent>
<extent>
<description>pass by value</description>
<source_reference file="../src/mae/fl/math.cpp" line="188" />
</extent>
<extent>
<description>pass by value</description>
<source_reference file="../src/mae/fl/math.cpp" line="235" />
</extent>
<extent>
<description>pass by value</description>
<source_reference file="../src/mae/fl/math.cpp" line="235" />
</extent>
<extent>
<description>pass by value</description>
<source_reference file="../src/mae/fl/math.cpp" line="235" />
</extent>
<extent>
<description>pass by value</description>
<source_reference file="../src/mae/fl/math.cpp" line="245" />
</extent>
<extent>
<description>pass by value</description>
<source_reference file="../src/mae/fl/math.cpp" line="245" />
</extent>
<extent>
<description>pass by value</description>
<source_reference file="../src/mae/fl/math.cpp" line="245" />
</extent>
<name>vector</name>
<visible>true</visible>
<concrete>true</concrete>
<extent>
<description>pass by value</description>
<source_reference file="../src/mae/fl/math.hpp" line="89" />
</extent>
<extent>
<description>pass by value</description>
<source_reference file="../src/mae/fl/math.hpp" line="97" />
</extent>
<extent>
<description>pass by value</description>
<source_reference file="../src/mae/fl/math.cpp" line="68" />
</extent>
<extent>
<description>pass by value</description>
<source_reference file="../src/mae/fl/math.cpp" line="88" />
</extent>
</supplier_module>
</module>
</structural_detail>
</CCCC_Project>
